deepchecks_installer/__init__.py
deepchecks_installer/cli.py
deepchecks_installer/deploy-oss.sh
deepchecks_installer-0.3.dist-info/METADATA
deepchecks_installer-0.3.dist-info/WHEEL
deepchecks_installer-0.3.dist-info/entry_points.txt
deepchecks_installer-0.3.dist-info/top_level.txt
deepchecks_installer-0.3.dist-info/RECORD
