Metadata-Version: 2.1
Name: deepchecks-installer
Version: 0.3
Requires-Dist: argparse
